crbutils/__init__.py
crbutils/modeval.py
crbutils-1.0.1.dist-info/METADATA
crbutils-1.0.1.dist-info/WHEEL
crbutils-1.0.1.dist-info/RECORD
