Metadata-Version: 2.1
Name: crbutils
Version: 1.0.1
Summary: A DS utility library
Author: Christopher Bonham
Requires-Python: ==3.9.13
Classifier: Programming Language :: Python :: 3
Requires-Dist: numpy (>=1.24.2)
Requires-Dist: plotly (>=5.13.1)
Requires-Dist: scikit-learn (>=1.2.1)
Requires-Dist: toml (>=0.10.2)
